BetterADBSync/SAOLogging.py
BetterADBSync/__init__.py
BetterADBSync/argparsing.py
BetterADBSync/FileSystems/Android.py
BetterADBSync/FileSystems/Base.py
BetterADBSync/FileSystems/Local.py
BetterADBSync/FileSystems/__init__.py
adbclone-0.0.4.dist-info/LICENSE
adbclone-0.0.4.dist-info/METADATA
adbclone-0.0.4.dist-info/WHEEL
adbclone-0.0.4.dist-info/entry_points.txt
adbclone-0.0.4.dist-info/top_level.txt
adbclone-0.0.4.dist-info/RECORD
