Metadata-Version: 2.1
Name: adbclone
Version: 0.0.4
Summary: Better version of adb-sync for Python3
License: 
Project-URL: Homepage, https://github.com/gautamajay52/adbclone
License-File: LICENSE
Requires-Dist: rich
